{
  "Author": "Aireil",
  "Name": "FF Logs Viewer",
  "InternalName": "FFLogsViewer",
  "AssemblyVersion": "1.5.7.2",
  "Description": "在游戏里查看玩家在FFLogs上的数据的插件。",
  "ApplicableVersion": "any",
  "RepoUrl": "https://github.com/NukoOoOoOoO/FFLogsViewer",
  "Tags": [
    "FFLogs",
    "FFLog",
    "FFLo",
    "FFL"
  ],
  "DalamudApiLevel": 6,
  "LoadPriority": 0,
  "ImageUrls": [
    "https://github.com/NukoOoOoOoO/FFLogsViewer/raw/CN-Ver/res/banner.png"
  ],
  "IconUrl": "https://github.com/NukoOoOoOoO/FFLogsViewer/raw/CN-Ver/res/icon.png",
  "Punchline": "View FF Logs ranking percentiles in-game.",
  "Changelog": "- Add support for Endsinger Extreme\n- Fix search and host name for the Chinese client (by LittleNightmare)"
}